napari_plot_profile/__init__.py
napari_plot_profile/_dock_widget.py
napari_plot_profile/_functions.py
napari_plot_profile/_tests/__init__.py
napari_plot_profile/_tests/test_dock_widget.py
napari_plot_profile/_tests/test_functions.py
napari_plot_profile-0.2.2.dist-info/LICENSE
napari_plot_profile-0.2.2.dist-info/METADATA
napari_plot_profile-0.2.2.dist-info/WHEEL
napari_plot_profile-0.2.2.dist-info/entry_points.txt
napari_plot_profile-0.2.2.dist-info/top_level.txt
napari_plot_profile-0.2.2.dist-info/RECORD
