Metadata-Version: 2.1
Name: napari-plot-profile
Version: 0.2.2
Summary: Plot intensity along a line and create topographical views in napari
Home-page: https://github.com/haesleinhuepf/napari-plot-profile
Author: Robert Haase, Marcelo Leomil Zoccoler
Author-email: robert.haase@tu-dresden.de
License: BSD-3-Clause
Project-URL: Bug Tracker, https://github.com/haesleinhuepf/napari-plot-profile/issues
Project-URL: Documentation, https://github.com/haesleinhuepf/napari-plot-profile#README.md
Project-URL: Source Code, https://github.com/haesleinhuepf/napari-plot-profile
Project-URL: User Support, https://github.com/haesleinhuepf/napari-plot-profile/issues
Classifier: Development Status :: 3 - Alpha
Classifier: Intended Audience :: Science/Research
Classifier: Framework :: napari
Classifier: Topic :: Scientific/Engineering :: Image Processing
Classifier: Topic :: Scientific/Engineering :: Information Analysis
Classifier: Programming Language :: Python
Classifier: Programming Language :: Python :: 3
Classifier: Programming Language :: Python :: 3.7
Classifier: Programming Language :: Python :: 3.8
Classifier: Programming Language :: Python :: 3.9
Classifier: Operating System :: OS Independent
Classifier: License :: OSI Approved :: BSD License
Requires-Python: >=3.7
License-File: LICENSE
Requires-Dist: napari-plugin-engine (>=0.1.4)
Requires-Dist: numpy
Requires-Dist: pyqtgraph
Requires-Dist: napari
Requires-Dist: napari-tools-menu
Requires-Dist: napari-skimage-regionprops (>=0.2.4)
Requires-Dist: imageio (!=2.22.1)
